init_data/__init__.py
init_data/main.py
init_data/py.typed
init_data_python-1.0.1.dist-info/LICENSE
init_data_python-1.0.1.dist-info/METADATA
init_data_python-1.0.1.dist-info/WHEEL
init_data_python-1.0.1.dist-info/top_level.txt
init_data_python-1.0.1.dist-info/RECORD
