Metadata-Version: 2.2
Name: init-data-python
Version: 1.0.1
Summary: A Python library that offers simple interface for validating Telegram Mini App initialization data.
Author-email: artender <artem1347929@gmail.com>
License: MIT License
Requires-Python: >=3.12
License-File: LICENSE
